py_jsonrpc_lite-0.1.dist-info/DESCRIPTION.rst
py_jsonrpc_lite-0.1.dist-info/METADATA
py_jsonrpc_lite-0.1.dist-info/RECORD
py_jsonrpc_lite-0.1.dist-info/WHEEL
py_jsonrpc_lite-0.1.dist-info/metadata.json
py_jsonrpc_lite-0.1.dist-info/top_level.txt
pyjsonrpclite/__init__.py
pyjsonrpclite/jsonrpc.py
