Metadata-Version: 2.0
Name: py-jsonrpc-lite
Version: 0.1
Summary: Parse and Serialize JSON-RPC 2.0 messages in Python
Home-page: https://github.com/r3code/py-jsonrpc-lite
Author: Dmitriy S. Sinyavskiy
Author-email: contact@r3code.ru
License: MIT
Platform: UNKNOWN
Classifier: Development Status :: 4 - Beta
Classifier: Environment :: Console
Classifier: License :: OSI Approved :: MIT License
Classifier: Natural Language :: English
Classifier: Operating System :: OS Independent
Classifier: Programming Language :: Python :: 2.7
Classifier: Programming Language :: Python :: Implementation :: PyPy
Classifier: Topic :: Software Development :: Libraries :: Python Modules
